agentics/__init__.py
agentics/agent.py
agentics/tool_box.py
agentics-lundmj/__init__.py
agentics-lundmj/agent.py
agentics-lundmj/tool_box.py
agentics_lundmj/__init__.py
agentics_lundmj/agent.py
agentics_lundmj/tool_box.py
agentics_lundmj-1.0.1.dist-info/METADATA
agentics_lundmj-1.0.1.dist-info/WHEEL
agentics_lundmj-1.0.1.dist-info/top_level.txt
agentics_lundmj-1.0.1.dist-info/RECORD
