Metadata-Version: 2.1
Name: agentics_lundmj
Version: 1.0.1
Summary: A package for building intelligent agents through OpenAI's API.
Home-page: https://github.com/lundmj/aiAgents
Author: Matthew Lund
Author-email: lundmatthewj@gmail.com
Classifier: Programming Language :: Python :: 3
Classifier: License :: OSI Approved :: MIT License
Classifier: Operating System :: OS Independent
Requires-Python: >=3.7
Requires-Dist: openai >=2.7.1
